[
    {
        "name": "id",
        "dbType": "bigInteger,true,true",
        "htmlType": null,
        "validations": null,
        "searchable": false,
        "fillable": false,
        "primary": true,
        "inForm": false,
        "inIndex": false,
        "inView": false
    },
    {
        "name": "nome",
        "dbType": "string,191",
        "htmlType": "text",
        "validations": "required",
        "searchable": true,
        "fillable": true,
        "primary": false,
        "inForm": true,
        "inIndex": true,
        "inView": true
    },
    {
        "name": "endereco",
        "dbType": "string,191",
        "htmlType": "text",
        "validations": "required",
        "searchable": true,
        "fillable": true,
        "primary": false,
        "inForm": true,
        "inIndex": true,
        "inView": true
    },
    {
        "name": "bairro",
        "dbType": "string,191",
        "htmlType": "text",
        "validations": "required",
        "searchable": true,
        "fillable": true,
        "primary": false,
        "inForm": true,
        "inIndex": true,
        "inView": true
    },
    {
        "name": "cidade",
        "dbType": "string,191",
        "htmlType": "text",
        "validations": "required",
        "searchable": true,
        "fillable": true,
        "primary": false,
        "inForm": true,
        "inIndex": true,
        "inView": true
    },
    {
        "name": "estado",
        "dbType": "string,191",
        "htmlType": "text",
        "validations": "required",
        "searchable": true,
        "fillable": true,
        "primary": false,
        "inForm": true,
        "inIndex": true,
        "inView": true
    },
    {
        "name": "cep",
        "dbType": "string,191",
        "htmlType": "text",
        "validations": "required",
        "searchable": true,
        "fillable": true,
        "primary": false,
        "inForm": true,
        "inIndex": true,
        "inView": true
    },
    {
        "name": "ddd1",
        "dbType": "string,191",
        "htmlType": "text",
        "validations": "required",
        "searchable": true,
        "fillable": true,
        "primary": false,
        "inForm": true,
        "inIndex": true,
        "inView": true
    },
    {
        "name": "telefone1",
        "dbType": "string,191",
        "htmlType": "text",
        "validations": "required",
        "searchable": true,
        "fillable": true,
        "primary": false,
        "inForm": true,
        "inIndex": true,
        "inView": true
    },
    {
        "name": "ddd2",
        "dbType": "string,191",
        "htmlType": "text",
        "validations": "required",
        "searchable": true,
        "fillable": true,
        "primary": false,
        "inForm": true,
        "inIndex": true,
        "inView": true
    },
    {
        "name": "telefone2",
        "dbType": "string,191",
        "htmlType": "text",
        "validations": "required",
        "searchable": true,
        "fillable": true,
        "primary": false,
        "inForm": true,
        "inIndex": true,
        "inView": true
    },
    {
        "name": "ddd3",
        "dbType": "string,191",
        "htmlType": "text",
        "validations": "required",
        "searchable": true,
        "fillable": true,
        "primary": false,
        "inForm": true,
        "inIndex": true,
        "inView": true
    },
    {
        "name": "celular",
        "dbType": "string,191",
        "htmlType": "text",
        "validations": "required",
        "searchable": true,
        "fillable": true,
        "primary": false,
        "inForm": true,
        "inIndex": true,
        "inView": true
    },
    {
        "name": "custo",
        "dbType": "string,191",
        "htmlType": "text",
        "validations": "required",
        "searchable": true,
        "fillable": true,
        "primary": false,
        "inForm": true,
        "inIndex": true,
        "inView": true
    },
    {
        "name": "email",
        "dbType": "string,191",
        "htmlType": "text",
        "validations": "required",
        "searchable": true,
        "fillable": true,
        "primary": false,
        "inForm": true,
        "inIndex": true,
        "inView": true
    },
    {
        "name": "cargo",
        "dbType": "string,191",
        "htmlType": "text",
        "validations": "required",
        "searchable": true,
        "fillable": true,
        "primary": false,
        "inForm": true,
        "inIndex": true,
        "inView": true
    },
    {
        "name": "salario",
        "dbType": "string,191",
        "htmlType": "text",
        "validations": "required",
        "searchable": true,
        "fillable": true,
        "primary": false,
        "inForm": true,
        "inIndex": true,
        "inView": true
    },
    {
        "name": "status",
        "dbType": "integer,false",
        "htmlType": null,
        "validations": "required",
        "searchable": true,
        "fillable": true,
        "primary": false,
        "inForm": true,
        "inIndex": true,
        "inView": true
    },
    {
        "name": "rg",
        "dbType": "string,191",
        "htmlType": "text",
        "validations": "required",
        "searchable": true,
        "fillable": true,
        "primary": false,
        "inForm": true,
        "inIndex": true,
        "inView": true
    },
    {
        "name": "cpf",
        "dbType": "string,191",
        "htmlType": "text",
        "validations": "required",
        "searchable": true,
        "fillable": true,
        "primary": false,
        "inForm": true,
        "inIndex": true,
        "inView": true
    },
    {
        "name": "ctps",
        "dbType": "string,191",
        "htmlType": "text",
        "validations": "required",
        "searchable": true,
        "fillable": true,
        "primary": false,
        "inForm": true,
        "inIndex": true,
        "inView": true
    },
    {
        "name": "registro",
        "dbType": "string,191",
        "htmlType": "text",
        "validations": "required",
        "searchable": true,
        "fillable": true,
        "primary": false,
        "inForm": true,
        "inIndex": true,
        "inView": true
    },
    {
        "name": "empresa",
        "dbType": "string,191",
        "htmlType": "text",
        "validations": "required",
        "searchable": true,
        "fillable": true,
        "primary": false,
        "inForm": true,
        "inIndex": true,
        "inView": true
    },
    {
        "name": "data_aso",
        "dbType": "string,191",
        "htmlType": "text",
        "validations": "required",
        "searchable": true,
        "fillable": true,
        "primary": false,
        "inForm": true,
        "inIndex": true,
        "inView": true
    },
    {
        "name": "data_venc_aso",
        "dbType": "string,191",
        "htmlType": "text",
        "validations": "required",
        "searchable": true,
        "fillable": true,
        "primary": false,
        "inForm": true,
        "inIndex": true,
        "inView": true
    },
    {
        "name": "exames",
        "dbType": "string,191",
        "htmlType": "text",
        "validations": "required",
        "searchable": true,
        "fillable": true,
        "primary": false,
        "inForm": true,
        "inIndex": true,
        "inView": true
    },
    {
        "name": "deleted_at",
        "dbType": "datetime:nullable",
        "htmlType": "date",
        "validations": null,
        "searchable": false,
        "fillable": false,
        "primary": false,
        "inForm": false,
        "inIndex": false,
        "inView": false
    },
    {
        "name": "created_at",
        "dbType": "datetime:nullable",
        "htmlType": "date",
        "validations": null,
        "searchable": false,
        "fillable": false,
        "primary": false,
        "inForm": false,
        "inIndex": false,
        "inView": false
    },
    {
        "name": "updated_at",
        "dbType": "datetime:nullable",
        "htmlType": "date",
        "validations": null,
        "searchable": false,
        "fillable": false,
        "primary": false,
        "inForm": false,
        "inIndex": false,
        "inView": false
    }
]